LICENSE
MANIFEST.in
README.rst
requirements.txt
setup.py
dj_dynamodb_sessions.egg-info/PKG-INFO
dj_dynamodb_sessions.egg-info/SOURCES.txt
dj_dynamodb_sessions.egg-info/dependency_links.txt
dj_dynamodb_sessions.egg-info/requires.txt
dj_dynamodb_sessions.egg-info/top_level.txt
dynamodb_sessions/__init__.py
dynamodb_sessions/models.py
dynamodb_sessions/tests.py
dynamodb_sessions/backends/__init__.py
dynamodb_sessions/backends/cached_dynamodb.py
dynamodb_sessions/backends/db.py
dynamodb_sessions/backends/dynamodb.py
dynamodb_sessions/management/__init__.py
dynamodb_sessions/management/commands/__init__.py
dynamodb_sessions/management/commands/create_session_table.py
dynamodb_sessions/management/commands/delete_session_table.py